ghasedak_sms/__init__.py
ghasedak_sms/dto.py
ghasedak_sms/ghasedak.py
ghasedak_sms/helper.py
ghasedak_sms/test_ghasedak.py
ghasedak_sms/enums/__init__.py
ghasedak_sms/enums/message_id_type.py
ghasedak_sms/enums/send_status.py
ghasedak_sms-1.0.3.dist-info/LICENSE
ghasedak_sms-1.0.3.dist-info/METADATA
ghasedak_sms-1.0.3.dist-info/WHEEL
ghasedak_sms-1.0.3.dist-info/top_level.txt
ghasedak_sms-1.0.3.dist-info/RECORD
