Metadata-Version: 2.1
Name: ghasedak_sms
Version: 1.0.3
Summary: Python package for Ghasedak SMS API
Home-page: http://sms.ghasedak.me
Author: Ghasedak Developers Team
Author-email: hasheminasab97@gmail.com
Classifier: Development Status :: 4 - Beta
Classifier: Intended Audience :: Developers
Classifier: License :: OSI Approved :: MIT License
Classifier: Programming Language :: Python :: 3
Classifier: Programming Language :: Python :: 3.7
Classifier: Programming Language :: Python :: 3.8
Classifier: Programming Language :: Python :: 3.9
Classifier: Programming Language :: Python :: 3.10
Classifier: Programming Language :: Python :: 3.11
Requires-Python: >=3.6
License-File: LICENSE
Requires-Dist: requests
